ftopsis_class/__init__.py
ftopsis_class/main.py
ftopsis_class-0.1.dist-info/METADATA
ftopsis_class-0.1.dist-info/WHEEL
ftopsis_class-0.1.dist-info/top_level.txt
ftopsis_class-0.1.dist-info/RECORD
