Metadata-Version: 2.1
Name: ftopsis-class
Version: 0.1
Summary: FTOPSIS Class implemented in python
Home-page: https://github.com/lucasccampos/ftopsis_class
Author: Lucas C., Ian F., Matheus F., Rodrigo B., Arthur C.
License: UNKNOWN
Platform: UNKNOWN
Requires-Dist: numpy (>=1.26.4)
Requires-Dist: pandas (>=2.2.1)
